loaders/__init__.py
loaders/loader.py
preprocessing/__init__.py
preprocessing/preprocess.py
financial_ts-0.1.39.dist-info/LICENSE
financial_ts-0.1.39.dist-info/METADATA
financial_ts-0.1.39.dist-info/WHEEL
financial_ts-0.1.39.dist-info/top_level.txt
financial_ts-0.1.39.dist-info/RECORD
