Metadata-Version: 2.1
Name: financial-ts
Version: 0.1.39
Summary: Python module for loading time series data.
Home-page: https://github.com/gilberto-BE/financial_ts
Author: Gilberto Batres-Estrada
Author-email: g.batres.estrada@gmail.com
License: UNKNOWN
Project-URL: Bug Tracker, https://github.com/gilberto-BE/financial_ts/issues
Platform: UNKNOWN
Classifier: Programming Language :: Python :: 3
Classifier: License :: OSI Approved :: MIT License
Classifier: Operating System :: OS Independent
Requires-Python: >=3.6
License-File: LICENSE
